hmg/__init__.py
hmg/client.py
hmg/hangman.py
hmg/server.py
hmg/ui.py
hmg/word_utils.py
hmg-0.1.data/scripts/hmg-client
hmg-0.1.data/scripts/hmg-server
hmg-0.1.dist-info/LICENSE
hmg-0.1.dist-info/METADATA
hmg-0.1.dist-info/WHEEL
hmg-0.1.dist-info/top_level.txt
hmg-0.1.dist-info/RECORD
