Metadata-Version: 2.1
Name: hmg
Version: 0.1
Summary: A simple Hangman Multiplayer Game by CLI in python!
Author: Rodrigo Acosta
License: UNKNOWN
Platform: UNKNOWN
License-File: LICENSE
Requires-Dist: requests
Requires-Dist: rich
Provides-Extra: dev
Requires-Dist: pytest ; extra == 'dev'
Requires-Dist: pytest-cov ; extra == 'dev'
Requires-Dist: black ; extra == 'dev'
Requires-Dist: flake8 ; extra == 'dev'
